aikido_firewall/__init__.py
aikido_firewall/aws_lambda/__init__.py
aikido_firewall/background_process/__init__.py
aikido_firewall/background_process/aikido_background_process.py
aikido_firewall/background_process/api/__init__.py
aikido_firewall/background_process/api/http_api.py
aikido_firewall/background_process/api/http_api_ratelimited.py
aikido_firewall/background_process/api/http_api_ratelimited_test.py
aikido_firewall/background_process/api/http_api_test.py
aikido_firewall/background_process/api/init_test.py
aikido_firewall/background_process/cloud_connection_manager/__init__.py
aikido_firewall/background_process/cloud_connection_manager/get_manager_info.py
aikido_firewall/background_process/cloud_connection_manager/get_manager_info_test.py
aikido_firewall/background_process/cloud_connection_manager/on_detected_attack.py
aikido_firewall/background_process/cloud_connection_manager/on_detected_attack_test.py
aikido_firewall/background_process/cloud_connection_manager/on_start.py
aikido_firewall/background_process/cloud_connection_manager/on_start_test.py
aikido_firewall/background_process/cloud_connection_manager/send_heartbeat.py
aikido_firewall/background_process/cloud_connection_manager/update_service_config.py
aikido_firewall/background_process/commands/__init__.py
aikido_firewall/background_process/commands/attack.py
aikido_firewall/background_process/commands/attack_test.py
aikido_firewall/background_process/commands/fetch_initial_metadata.py
aikido_firewall/background_process/commands/hostnames_add.py
aikido_firewall/background_process/commands/is_ip_allowed.py
aikido_firewall/background_process/commands/kill.py
aikido_firewall/background_process/commands/ping.py
aikido_firewall/background_process/commands/read_property.py
aikido_firewall/background_process/commands/read_property_test.py
aikido_firewall/background_process/commands/route.py
aikido_firewall/background_process/commands/route_test.py
aikido_firewall-1.0.4.dist-info/LICENSE
aikido_firewall-1.0.4.dist-info/METADATA
aikido_firewall-1.0.4.dist-info/WHEEL
aikido_firewall-1.0.4.dist-info/RECORD
