Metadata-Version: 2.1
Name: aikido_firewall
Version: 1.0.4
Summary: Aikido Zen for Python
Home-page: https://www.aikido.dev/runtime/firewall/
License: AGPL-3.0-or-later
Keywords: web application firewall,WAF,cybersecurity,security,firewall,web security,application security,threat detection,intrusion prevention,DDoS protection,malware protection,Python,Python 3,network security,data protection,secure coding,vulnerability management,API security,SSL/TLS,penetration testing
Author: Aikido Security
Author-email: help@aikido.dev
Requires-Python: >=3.8,<4.0
Classifier: Environment :: Web Environment
Classifier: Intended Audience :: Developers
Classifier: Intended Audience :: System Administrators
Classifier: License :: OSI Approved :: GNU Affero General Public License v3 or later (AGPLv3+)
Classifier: Operating System :: POSIX :: Linux
Classifier: Programming Language :: Python :: 3
Classifier: Programming Language :: Python :: 3.8
Classifier: Programming Language :: Python :: 3.9
Classifier: Programming Language :: Python :: 3.10
Classifier: Programming Language :: Python :: 3.11
Classifier: Programming Language :: Python :: 3.12
Classifier: Programming Language :: Python :: 3 :: Only
Classifier: Topic :: Security
Requires-Dist: python-dotenv (>=1.0.1,<2.0.0)
Requires-Dist: regex (>=2024.5.15,<2025.0.0)
Requires-Dist: requests (>=2.32.3,<3.0.0)
Project-URL: Bug Tracker, https://github.com/AikidoSec/firewall-python/issues
Project-URL: Bug Bounty, https://app.intigriti.com/programs/aikido
Project-URL: Homepage, https://www.aikido.dev/runtime/firewall
Project-URL: Source, https://github.com/AikidoSec/firewall-python
